sparqlc/__init__.py
sparqlc/datatypes.py
sparqlc/exception.py
sparqlc/n3_parser.py
sparqlc/query.py
sparqlc/result_set.py
sparqlc/service.py
sparqlc/service_base.py
sparqlc/sparql-connect.py
sparqlc/version.py
sparqlc/version.txt
sparql_connector-0.0.5.dist-info/LICENSE
sparql_connector-0.0.5.dist-info/METADATA
sparql_connector-0.0.5.dist-info/WHEEL
sparql_connector-0.0.5.dist-info/top_level.txt
sparql_connector-0.0.5.dist-info/RECORD
