Metadata-Version: 2.1
Name: sparql-connector
Version: 0.0.5
Summary: SPARQL connector based on sparql-client library
Home-page: https://github.com/vlastocom/sparql-connector
Author: Vlastimil Chvojka
Author-email: 9798475+vlastocom@users.noreply.github.com
Project-URL: Bug Tracker, https://github.com/vlastocom/sparql-connector/issues
Classifier: Programming Language :: Python :: 3.10
Classifier: License :: OSI Approved :: Mozilla Public License 2.0 (MPL 2.0)
Classifier: Operating System :: OS Independent
Requires-Python: >=3.10
License-File: LICENSE
Requires-Dist: overrides (~=7.3.1)
Requires-Dist: python-dateutil (~=2.8.2)
Requires-Dist: urllib3 (~=1.26.12)
